kll/__init__.py
kll/__main__.py
kll/kll
kll/common/README.md
kll/common/__init__.py
kll/common/channel.py
kll/common/context.py
kll/common/emitter.py
kll/common/expression.py
kll/common/file.py
kll/common/id.py
kll/common/modifier.py
kll/common/organization.py
kll/common/parse.py
kll/common/position.py
kll/common/schedule.py
kll/common/stage.py
kll/common/suggestions.py
kll/emitters/README.md
kll/emitters/__init__.py
kll/emitters/emitters.py
kll/emitters/configurator/__init__.py
kll/emitters/configurator/configurator.py
kll/emitters/kiibohd/__init__.py
kll/emitters/kiibohd/kiibohd.py
kll/emitters/kll/__init__.py
kll/emitters/kll/kll.py
kll/emitters/none/__init__.py
kll/emitters/none/none.py
kll/emitters/state/__init__.py
kll/emitters/state/state.py
kll/examples/assignment.kll
kll/examples/capabilitiesExample.kll
kll/examples/colemak.kll
kll/examples/defaultMapExample.kll
kll/examples/example.kll
kll/examples/example2.kll
kll/examples/hhkbpro2.kll
kll/examples/leds.kll
kll/examples/leds2.kll
kll/examples/mapping.kll
kll/examples/md1Map.kll
kll/examples/nonetest.kll
kll/examples/simple1.kll
kll/examples/simple2.kll
kll/examples/simpleExample.kll
kll/examples/state_scheduling.kll
kll/examples/triggers.kll
kll/examples/utf8.kll
kll/examples/locale/base.locale-test.kll
kll/examples/locale/de_DE.locale-test.kll
kll/extern/README.md
kll/extern/funcparserlib/__init__.py
kll/extern/funcparserlib/lexer.py
kll/extern/funcparserlib/parser.py
kll/extern/funcparserlib/util.py
kll/layouts/Rapoo_E9070_Fn.kll
kll/layouts/animation_test.kll
kll/layouts/colemak-dh.kll
kll/layouts/colemak.kll
kll/layouts/hhkbpro2_shiftLeft.kll
kll/layouts/hhkbpro2_slim.kll
kll/layouts/kishsaver_unix1.kll
kll/layouts/kishsaver_unix2.kll
kll/layouts/klltest.kll
kll/layouts/klltest_default.kll
kll/layouts/ktype_demo.kll
kll/layouts/lcdFuncMap.kll
kll/layouts/mouseTest.kll
kll/layouts/remote_reload.kll
kll/layouts/stdFuncMap.kll
kll/layouts/tab_function.kll
kll/layouts/usb_debug.kll
kll-0.5.7.16.dist-info/entry_points.txt
kll-0.5.7.16.dist-info/LICENSE
kll-0.5.7.16.dist-info/WHEEL
kll-0.5.7.16.dist-info/METADATA
kll-0.5.7.16.dist-info/RECORD
