Metadata-Version: 2.1
Name: kll
Version: 0.5.7.16
Summary: KLL Compiler
Home-page: https://github.com/kiibohd/kll
License: UNKNOWN
Author: Jacob Alexander
Author-email: haata@kiibohd.com
Requires-Python: >=3.5
Classifier: Topic :: Software Development :: Compilers
Classifier: Intended Audience :: Developers
Classifier: License :: OSI Approved :: GNU General Public License v3 or later (GPLv3+)
Classifier: Programming Language :: Python :: 3
Requires-Dist: layouts>=0.4.9
Requires-Dist: gitpython
Requires-Dist: packaging
